{
  "project_info": {
    "project_number": "561928165518",
    "project_id": "a-thousand-words-dev",
    "storage_bucket": "a-thousand-words-dev.firebasestorage.app"
  },
  "client": [
    {
      "client_info": {
        "mobilesdk_app_id": "1:561928165518:android:4d6556c6bba636c93651df",
        "android_client_info": {
          "package_name": "com.tristans.athousandwords.dev"
        }
      },
      "oauth_client": [],
      "api_key": [
        {
          "current_key": "AIzaSyAZObIwLfZVujEUEtKTD6qZiLCG79pzLcI"
        }
      ],
      "services": {
        "appinvite_service": {
          "other_platform_oauth_client": []
        }
      }
    }
  ],
  "configuration_version": "1"
}